{
    "type": "minecraft:crafting_shaped",
    "pattern": [
        "RNR",
        "DTD",
        "RJR"
    ],
    "key": {
        "N": {
            "item": "minecraft:note_block"
        },
        "J": {
            "item": "minecraft:jukebox"
        },
        "D": {
            "item": "minecraft:diamond"
        },
        "R": {
            "item": "minecraft:redstone"
        },
        "T": {
            "item": "mimi:transmitter"
        }
    },
    "result": {
        "item": "mimi:musicplayer"
    }
}